exchange_calendars_extensions/api/__init__.py
exchange_calendars_extensions/api/changes.py
exchange_calendars_extensions/api/version.py
exchange_calendars_extensions_api-0.5.0.dist-info/METADATA
exchange_calendars_extensions_api-0.5.0.dist-info/WHEEL
exchange_calendars_extensions_api-0.5.0.dist-info/licenses/LICENSE
exchange_calendars_extensions_api-0.5.0.dist-info/RECORD
